{
  "Type": "FortDecoItemDefinition",
  "Name": "D_Wumba",
  "Flags": "RF_Public | RF_Standalone | RF_Transactional | RF_WasLoaded | RF_LoadCompleted",
  "Class": "UScriptClass'FortDecoItemDefinition'",
  "Package": "/Game/Athena/Items/Gameplay/Wumba/D_Wumba",
  "Properties": {
    "BlueprintClass": {
      "AssetPathName": "/Game/Athena/Items/Gameplay/Wumba/B_Athena_Wumba.B_Athena_Wumba_C",
      "SubPathString": ""
    },
    "PlacementPreviewClass": {
      "AssetPathName": "/Game/Athena/Items/Gameplay/Wumba/DecoPreview_Wumba.DecoPreview_Wumba_C",
      "SubPathString": ""
    },
    "bCanBePlacedOnEnemyBuildings": true,
    "GridSnapSizeOverride": 512.0,
    "PlacementTypeOverride": "EPlacementType::Grid",
    "bIgnoreCollisionWithStructuralGridActors": true,
    "bIgnoreCollisionWithFortStaticMeshActors": true,
    "bAllowPlacementOnWorldGeometry": false,
    "bDestroySmallObjectsWhenPlaced": true,
    "bSetOwningPlayerForSpawnedDeco": true,
    "bSetSpawnedDecoOnPlayerTeam": false,
    "bCancelToolWhenPlaced": false,
    "bCancelAbilityOnUnequip": false,
    "bRequiresPermissionToEditWorld": true,
    "bAutoCreateAttachmentBuilding": true,
    "bShowPreviewOnPressHeld": true,
    "AutoCreateAttachmentBuildingResourceType": "EFortResourceType::Metal",
    "AutoCreateAttachmentBuildingShapes": [
      {
        "AssetPathName": "/Game/Building/EditModePatterns/Floor/EMP_Floor_Floor.EMP_Floor_Floor",
        "SubPathString": ""
      }
    ],
    "AllowedShapes": [
      {
        "AssetPathName": "/Game/Building/EditModePatterns/Floor/EMP_Floor_Floor.EMP_Floor_Floor",
        "SubPathString": ""
      }
    ],
    "WeaponActorClass": {
      "AssetPathName": "/Game/Athena/Items/Gameplay/Wumba/DA_Wumba.DA_Wumba_C",
      "SubPathString": ""
    },
    "ActualAnalyticFNames": [
      "Tag:Deco:d_wumba"
    ],
    "ItemName": {
      "Namespace": "",
      "Key": "13AC11E14B6B12E4AA74478E741221CA",
      "SourceString": "Upgrade Bench",
      "LocalizedString": "Upgrade Bench"
    },
    "DataList": [
      {
        "Traits": [
          "Item.Trait.AutoCombineStacks",
          "Item.Trait.Transient"
        ]
      },
      {
        "SearchTags": {
          "Namespace": "",
          "Key": "351DD3F340DB50701AA6B9AE8088D4D1",
          "SourceString": "Air Strike",
          "LocalizedString": "Air Strike"
        }
      },
      {
        "Icon": {
          "AssetPathName": "/Game/Global/Textures/Default/DefaultUI/T_Placeholder_Generic.T_Placeholder_Generic",
          "SubPathString": ""
        }
      },
      {
        "Tags": [
          "Rarity.Common",
          "Trap.ExtraPiece.Cost.Ignore",
          "Athena.ItemAction.Place"
        ]
      },
      {
        "Rarity": "EFortRarity::Common"
      }
    ]
  }
}