{
  "Type": "JunoBuildInstructionsItemDefinition",
  "Name": "JBID_Prop_BB_LowSurface_M_06x06_01",
  "Flags": "RF_Public | RF_Standalone | RF_Transactional | RF_WasLoaded | RF_LoadCompleted",
  "Class": "UScriptClass'JunoBuildInstructionsItemDefinition'",
  "Package": "/JunoTheme_BriteBomb/Props/JBID/JBID_Prop_BB_LowSurface_M_06x06_01",
  "Properties": {
    "bGiveResourcesOnDestroy": true,
    "SelfCraftingFormulaName": "JBID_Prop_BB_LowSurface_M_06x06_01",
    "SizeDescription": {
      "Namespace": "",
      "Key": "5E5663A63AC17CF3DE446281EA7678B0",
      "SourceString": "06x06",
      "LocalizedString": "06x06"
    },
    "SetDescription": {
      "Namespace": "",
      "Key": "5E5663A63AC17CF3DE446281F50DD9B2",
      "SourceString": "Brite Living",
      "LocalizedString": "Brite Living"
    },
    "ItemName": {
      "Namespace": "",
      "Key": "5E5663A63AC17CF3DE446281C7CA42CF",
      "SourceString": "BB LowSurface M - 6x6",
      "LocalizedString": "BB LowSurface M - 6x6"
    },
    "DataList": [
      {
        "Traits": [
          "Item.Trait.InventorySizeLimited"
        ]
      },
      {
        "Icon": {
          "AssetPathName": "/JunoTheme_BriteBomb/Props/JBID/Textures/T_Prop_BB_LowSurface_M_06x06_01.T_Prop_BB_LowSurface_M_06x06_01",
          "SubPathString": ""
        }
      },
      {
        "Tags": [
          "Juno.Crafting.IgnoreIngredientsForReveal",
          "Juno.Building.Prefab",
          "Juno.Building.Prop.Furniture.Surface.Low",
          "Juno.Building.Set.ID.BriteBomb"
        ]
      },
      {
        "ItemTypeNameOverride": {
          "CultureInvariantString": "BB LowSurface M - 6x6"
        }
      },
      {
        "ActorClass": {
          "AssetPathName": "/JunoTheme_BriteBomb/Props/BP/BP_GC_Prop_BB_LowSurface_M_06x06_01.BP_GC_Prop_BB_LowSurface_M_06x06_01_C",
          "SubPathString": ""
        }
      }
    ]
  }
}