{
  "Type": "VehicleCosmeticsItemDefinition_DriftTrail",
  "Name": "VCID_DriftTrail_HoloGlass",
  "Class": "UScriptClass'VehicleCosmeticsItemDefinition_DriftTrail'",
  "Flags": "RF_Public | RF_Standalone | RF_Transactional | RF_WasLoaded | RF_LoadCompleted",
  "Properties": {
    "CosmeticAttachments": [
      {
        "AssetPathName": "/VehicleCosmetics/DriftTrail/DriftTrail_HoloGlass/DriftCosmeticActor_HoloGlass.DriftCosmeticActor_HoloGlass_C",
        "SubPathString": ""
      }
    ],
    "AdditionalVariantInfos": [
      {
        "Key": {
          "TagName": "Cosmetics.Variant.Property.Vehicle.Painted.Black"
        },
        "Value": {
          "FloatParameters": [
            {
              "ParameterName": "ParticleColorVar",
              "ParameterValue": 30.0
            },
            {
              "ParameterName": "GlassColorVar",
              "ParameterValue": 1.0
            }
          ],
          "IntParameters": [],
          "ColorParameters": [
            {
              "ParameterName": "PaintedColor",
              "ParameterValue": {
                "R": 0.01,
                "G": 0.01,
                "B": 0.01,
                "A": 1.0,
                "Hex": "191919"
              }
            },
            {
              "ParameterName": "GlowColor",
              "ParameterValue": {
                "R": 0.05,
                "G": 0.05,
                "B": 0.05,
                "A": 1.0,
                "Hex": "3F3F3F"
              }
            },
            {
              "ParameterName": "CoreColor",
              "ParameterValue": {
                "R": 0.049707,
                "G": 0.049707,
                "B": 0.049707,
                "A": 1.0,
                "Hex": "3F3F3F"
              }
            },
            {
              "ParameterName": "GlassColor",
              "ParameterValue": {
                "R": 0.01,
                "G": 0.01,
                "B": 0.01,
                "A": 1.0,
                "Hex": "191919"
              }
            },
            {
              "ParameterName": "BoosterColor",
              "ParameterValue": {
                "R": 0.049707,
                "G": 0.049707,
                "B": 0.049707,
                "A": 1.0,
                "Hex": "3F3F3F"
              }
            },
            {
              "ParameterName": "AuxiliaryColor",
              "ParameterValue": {
                "R": 0.049707,
                "G": 0.049707,
                "B": 0.049707,
                "A": 1.0,
                "Hex": "3F3F3F"
              }
            }
          ]
        }
      },
      {
        "Key": {
          "TagName": "Cosmetics.Variant.Property.Vehicle.Painted.BurntSienna"
        },
        "Value": {
          "FloatParameters": [
            {
              "ParameterName": "ParticleColorVar",
              "ParameterValue": 10.0
            },
            {
              "ParameterName": "GlassColorVar",
              "ParameterValue": 5.0
            },
            {
              "ParameterName": "MaxGlassColor",
              "ParameterValue": 0.3
            },
            {
              "ParameterName": "MinimumGlassColor",
              "ParameterValue": 0.01
            }
          ],
          "IntParameters": [],
          "ColorParameters": [
            {
              "ParameterName": "PaintedColor",
              "ParameterValue": {
                "R": 0.046665,
                "G": 0.01096,
                "B": 0.001214,
                "A": 1.0,
                "Hex": "3D1B04"
              }
            },
            {
              "ParameterName": "GlowColor",
              "ParameterValue": {
                "R": 0.171441,
                "G": 0.039546,
                "B": 0.004777,
                "A": 1.0,
                "Hex": "73380F"
              }
            },
            {
              "ParameterName": "CoreColor",
              "ParameterValue": {
                "R": 0.046665,
                "G": 0.01096,
                "B": 0.001214,
                "A": 1.0,
                "Hex": "3D1B04"
              }
            },
            {
              "ParameterName": "GlassColor",
              "ParameterValue": {
                "R": 0.5,
                "G": 0.103034,
                "B": 0.01,
                "A": 1.0,
                "Hex": "BC5A19"
              }
            },
            {
              "ParameterName": "BoosterColor",
              "ParameterValue": {
                "R": 0.064803,
                "G": 0.020289,
                "B": 0.008023,
                "A": 1.0,
                "Hex": "482716"
              }
            },
            {
              "ParameterName": "AuxiliaryColor",
              "ParameterValue": {
                "R": 0.064803,
                "G": 0.020289,
                "B": 0.008023,
                "A": 1.0,
                "Hex": "482716"
              }
            }
          ]
        }
      },
      {
        "Key": {
          "TagName": "Cosmetics.Variant.Property.Vehicle.Painted.Cobalt"
        },
        "Value": {
          "FloatParameters": [
            {
              "ParameterName": "ParticleColorVar",
              "ParameterValue": 15.0
            },
            {
              "ParameterName": "GlassColorVar",
              "ParameterValue": 0.1
            },
            {
              "ParameterName": "MinimumGlassColor",
              "ParameterValue": 1.0
            },
            {
              "ParameterName": "MaxGlassColor",
              "ParameterValue": 1.0
            }
          ],
          "IntParameters": [],
          "ColorParameters": [
            {
              "ParameterName": "PaintedColor",
              "ParameterValue": {
                "R": 0.003999,
                "G": 0.136431,
                "B": 0.25,
                "A": 1.0,
                "Hex": "0C6789"
              }
            },
            {
              "ParameterName": "GlowColor",
              "ParameterValue": {
                "R": 0.218748,
                "G": 0.580617,
                "B": 3.0,
                "A": 1.0,
                "Hex": "81C9FF"
              }
            },
            {
              "ParameterName": "CoreColor",
              "ParameterValue": {
                "R": 0.182292,
                "G": 0.197419,
                "B": 1.0,
                "A": 1.0,
                "Hex": "767BFF"
              }
            },
            {
              "ParameterName": "GlassColor",
              "ParameterValue": {
                "R": 0.006512,
                "G": 0.141263,
                "B": 0.73791,
                "A": 1.0,
                "Hex": "1369DF"
              }
            },
            {
              "ParameterName": "BoosterColor",
              "ParameterValue": {
                "R": 0.0,
                "G": 0.0185,
                "B": 1.0,
                "A": 1.0,
                "Hex": "0025FF"
              }
            },
            {
              "ParameterName": "AuxiliaryColor",
              "ParameterValue": {
                "R": 0.0,
                "G": 0.0185,
                "B": 1.0,
                "A": 1.0,
                "Hex": "0025FF"
              }
            }
          ]
        }
      },
      {
        "Key": {
          "TagName": "Cosmetics.Variant.Property.Vehicle.Painted.Crimson"
        },
        "Value": {
          "FloatParameters": [
            {
              "ParameterName": "ParticleColorVar",
              "ParameterValue": 5.0
            },
            {
              "ParameterName": "GlassColorVar",
              "ParameterValue": 0.1
            },
            {
              "ParameterName": "MinimumGlassColor",
              "ParameterValue": 0.4
            },
            {
              "ParameterName": "MaxGlassColor",
              "ParameterValue": 2.0
            }
          ],
          "IntParameters": [],
          "ColorParameters": [
            {
              "ParameterName": "PaintedColor",
              "ParameterValue": {
                "R": 0.15,
                "G": 0.029688,
                "B": 0.032835,
                "A": 1.0,
                "Hex": "6C3032"
              }
            },
            {
              "ParameterName": "GlowColor",
              "ParameterValue": {
                "R": 3.0,
                "G": 0.562503,
                "B": 0.562503,
                "A": 1.0,
                "Hex": "FFC6C6"
              }
            },
            {
              "ParameterName": "CoreColor",
              "ParameterValue": {
                "R": 3.0,
                "G": 0.546875,
                "B": 0.546875,
                "A": 1.0,
                "Hex": "FFC3C3"
              }
            },
            {
              "ParameterName": "GlassColor",
              "ParameterValue": {
                "R": 0.83077,
                "G": 0.035601,
                "B": 0.036889,
                "A": 1.0,
                "Hex": "EB3536"
              }
            },
            {
              "ParameterName": "BoosterColor",
              "ParameterValue": {
                "R": 0.462077,
                "G": 0.0,
                "B": 0.012286,
                "A": 1.0,
                "Hex": "B5001D"
              }
            },
            {
              "ParameterName": "AuxiliaryColor",
              "ParameterValue": {
                "R": 0.462077,
                "G": 0.0,
                "B": 0.012286,
                "A": 1.0,
                "Hex": "B5001D"
              }
            }
          ]
        }
      },
      {
        "Key": {
          "TagName": "Cosmetics.Variant.Property.Vehicle.Painted.ForestGreen"
        },
        "Value": {
          "FloatParameters": [
            {
              "ParameterName": "ParticleColorVar",
              "ParameterValue": 10.0
            },
            {
              "ParameterName": "GlassColorVar",
              "ParameterValue": 0.1
            },
            {
              "ParameterName": "MinimumGlassColor",
              "ParameterValue": 3.5
            }
          ],
          "IntParameters": [],
          "ColorParameters": [
            {
              "ParameterName": "PaintedColor",
              "ParameterValue": {
                "R": 0.024739,
                "G": 0.25,
                "B": 0.036022,
                "A": 1.0,
                "Hex": "2B8935"
              }
            },
            {
              "ParameterName": "GlowColor",
              "ParameterValue": {
                "R": 0.296875,
                "G": 1.5,
                "B": 0.357135,
                "A": 1.0,
                "Hex": "94FFA1"
              }
            },
            {
              "ParameterName": "CoreColor",
              "ParameterValue": {
                "R": 0.296875,
                "G": 1.5,
                "B": 0.357135,
                "A": 1.0,
                "Hex": "94FFA1"
              }
            },
            {
              "ParameterName": "GlassColor",
              "ParameterValue": {
                "R": 0.019124,
                "G": 0.244792,
                "B": 0.021805,
                "A": 1.0,
                "Hex": "258828"
              }
            },
            {
              "ParameterName": "BoosterColor",
              "ParameterValue": {
                "R": 0.0,
                "G": 0.502886,
                "B": 0.025187,
                "A": 1.0,
                "Hex": "00BC2C"
              }
            },
            {
              "ParameterName": "AuxiliaryColor",
              "ParameterValue": {
                "R": 0.0,
                "G": 0.502886,
                "B": 0.025187,
                "A": 1.0,
                "Hex": "00BC2C"
              }
            }
          ]
        }
      },
      {
        "Key": {
          "TagName": "Cosmetics.Variant.Property.Vehicle.Painted.Grey"
        },
        "Value": {
          "FloatParameters": [
            {
              "ParameterName": "ParticleColorVar",
              "ParameterValue": 10.0
            },
            {
              "ParameterName": "GlassColorVar",
              "ParameterValue": 0.1
            },
            {
              "ParameterName": "MinimumGlassColor",
              "ParameterValue": 3.0
            },
            {
              "ParameterName": "MaxGlassColor",
              "ParameterValue": 10.0
            }
          ],
          "IntParameters": [],
          "ColorParameters": [
            {
              "ParameterName": "PaintedColor",
              "ParameterValue": {
                "R": 0.1,
                "G": 0.1,
                "B": 0.1,
                "A": 1.0,
                "Hex": "595959"
              }
            },
            {
              "ParameterName": "GlowColor",
              "ParameterValue": {
                "R": 0.505208,
                "G": 0.505208,
                "B": 0.505208,
                "A": 1.0,
                "Hex": "BDBDBD"
              }
            },
            {
              "ParameterName": "CoreColor",
              "ParameterValue": {
                "R": 0.505208,
                "G": 0.505208,
                "B": 0.505208,
                "A": 1.0,
                "Hex": "BDBDBD"
              }
            },
            {
              "ParameterName": "GlassColor",
              "ParameterValue": {
                "R": 0.036458,
                "G": 0.036458,
                "B": 0.036458,
                "A": 1.0,
                "Hex": "353535"
              }
            },
            {
              "ParameterName": "BoosterColor",
              "ParameterValue": {
                "R": 0.201556,
                "G": 0.201556,
                "B": 0.201556,
                "A": 1.0,
                "Hex": "7C7C7C"
              }
            },
            {
              "ParameterName": "AuxiliaryColor",
              "ParameterValue": {
                "R": 0.201556,
                "G": 0.201556,
                "B": 0.201556,
                "A": 1.0,
                "Hex": "7C7C7C"
              }
            }
          ]
        }
      },
      {
        "Key": {
          "TagName": "Cosmetics.Variant.Property.Vehicle.Painted.Lime"
        },
        "Value": {
          "FloatParameters": [
            {
              "ParameterName": "ParticleColorVar",
              "ParameterValue": 8.0
            },
            {
              "ParameterName": "GlassColorVar",
              "ParameterValue": 0.1
            },
            {
              "ParameterName": "MinimumGlassColor",
              "ParameterValue": 4.0
            }
          ],
          "IntParameters": [],
          "ColorParameters": [
            {
              "ParameterName": "PaintedColor",
              "ParameterValue": {
                "R": 0.133819,
                "G": 0.395833,
                "B": 0.0,
                "A": 1.0,
                "Hex": "66A900"
              }
            },
            {
              "ParameterName": "GlowColor",
              "ParameterValue": {
                "R": 0.519458,
                "G": 1.0,
                "B": 0.286465,
                "A": 1.0,
                "Hex": "BFFF92"
              }
            },
            {
              "ParameterName": "CoreColor",
              "ParameterValue": {
                "R": 0.519458,
                "G": 1.0,
                "B": 0.286465,
                "A": 1.0,
                "Hex": "BFFF92"
              }
            },
            {
              "ParameterName": "GlassColor",
              "ParameterValue": {
                "R": 0.0865,
                "G": 0.254152,
                "B": 0.0,
                "A": 1.0,
                "Hex": "538A00"
              }
            },
            {
              "ParameterName": "BoosterColor",
              "ParameterValue": {
                "R": 0.296138,
                "G": 0.590619,
                "B": 0.0,
                "A": 1.0,
                "Hex": "94CA00"
              }
            },
            {
              "ParameterName": "AuxiliaryColor",
              "ParameterValue": {
                "R": 0.296138,
                "G": 0.590619,
                "B": 0.0,
                "A": 1.0,
                "Hex": "94CA00"
              }
            }
          ]
        }
      },
      {
        "Key": {
          "TagName": "Cosmetics.Variant.Property.Vehicle.Painted.Orange"
        },
        "Value": {
          "FloatParameters": [
            {
              "ParameterName": "ParticleColorVar",
              "ParameterValue": 8.0
            },
            {
              "ParameterName": "GlassColorVar",
              "ParameterValue": 0.1
            },
            {
              "ParameterName": "MinimumGlassColor",
              "ParameterValue": 2.5
            }
          ],
          "IntParameters": [],
          "ColorParameters": [
            {
              "ParameterName": "PaintedColor",
              "ParameterValue": {
                "R": 0.3,
                "G": 0.063498,
                "B": 0.0,
                "A": 1.0,
                "Hex": "954700"
              }
            },
            {
              "ParameterName": "GlowColor",
              "ParameterValue": {
                "R": 1.0,
                "G": 0.392896,
                "B": 0.067708,
                "A": 1.0,
                "Hex": "FFA849"
              }
            },
            {
              "ParameterName": "CoreColor",
              "ParameterValue": {
                "R": 1.0,
                "G": 0.392896,
                "B": 0.067708,
                "A": 1.0,
                "Hex": "FFA849"
              }
            },
            {
              "ParameterName": "GlassColor",
              "ParameterValue": {
                "R": 0.328125,
                "G": 0.063311,
                "B": 0.0,
                "A": 1.0,
                "Hex": "9B4700"
              }
            },
            {
              "ParameterName": "BoosterColor",
              "ParameterValue": {
                "R": 0.672443,
                "G": 0.234551,
                "B": 0.0,
                "A": 1.0,
                "Hex": "D68500"
              }
            },
            {
              "ParameterName": "AuxiliaryColor",
              "ParameterValue": {
                "R": 0.672443,
                "G": 0.234551,
                "B": 0.0,
                "A": 1.0,
                "Hex": "D68500"
              }
            }
          ]
        }
      },
      {
        "Key": {
          "TagName": "Cosmetics.Variant.Property.Vehicle.Painted.Pink"
        },
        "Value": {
          "FloatParameters": [
            {
              "ParameterName": "ParticleColorVar",
              "ParameterValue": 10.0
            },
            {
              "ParameterName": "GlassColorVar",
              "ParameterValue": 0.1
            },
            {
              "ParameterName": "MinimumGlassColor",
              "ParameterValue": 1.5
            }
          ],
          "IntParameters": [],
          "ColorParameters": [
            {
              "ParameterName": "PaintedColor",
              "ParameterValue": {
                "R": 0.505208,
                "G": 0.121039,
                "B": 0.467,
                "A": 1.0,
                "Hex": "BD61B6"
              }
            },
            {
              "ParameterName": "GlowColor",
              "ParameterValue": {
                "R": 2.0,
                "G": 0.860695,
                "B": 1.898305,
                "A": 1.0,
                "Hex": "FFEFFF"
              }
            },
            {
              "ParameterName": "CoreColor",
              "ParameterValue": {
                "R": 2.0,
                "G": 0.729166,
                "B": 1.536794,
                "A": 1.0,
                "Hex": "FFDEFF"
              }
            },
            {
              "ParameterName": "GlassColor",
              "ParameterValue": {
                "R": 0.34375,
                "G": 0.14502,
                "B": 0.319239,
                "A": 1.0,
                "Hex": "9F6A99"
              }
            },
            {
              "ParameterName": "BoosterColor",
              "ParameterValue": {
                "R": 0.502886,
                "G": 0.061246,
                "B": 0.341914,
                "A": 1.0,
                "Hex": "BC469E"
              }
            },
            {
              "ParameterName": "AuxiliaryColor",
              "ParameterValue": {
                "R": 0.502886,
                "G": 0.061246,
                "B": 0.341914,
                "A": 1.0,
                "Hex": "BC469E"
              }
            }
          ]
        }
      },
      {
        "Key": {
          "TagName": "Cosmetics.Variant.Property.Vehicle.Painted.Purple"
        },
        "Value": {
          "FloatParameters": [
            {
              "ParameterName": "ParticleColorVar",
              "ParameterValue": 10.0
            },
            {
              "ParameterName": "GlassColorVar",
              "ParameterValue": 0.1
            },
            {
              "ParameterName": "MinimumGlassColor",
              "ParameterValue": 4.5
            },
            {
              "ParameterName": "MaxGlassColor",
              "ParameterValue": 6.0
            }
          ],
          "IntParameters": [],
          "ColorParameters": [
            {
              "ParameterName": "PaintedColor",
              "ParameterValue": {
                "R": 0.045828,
                "G": 0.013542,
                "B": 0.2,
                "A": 1.0,
                "Hex": "3C1E7C"
              }
            },
            {
              "ParameterName": "GlowColor",
              "ParameterValue": {
                "R": 0.830588,
                "G": 0.531243,
                "B": 2.0,
                "A": 1.0,
                "Hex": "EBC1FF"
              }
            },
            {
              "ParameterName": "CoreColor",
              "ParameterValue": {
                "R": 0.784031,
                "G": 0.388816,
                "B": 2.0,
                "A": 1.0,
                "Hex": "E5A8FF"
              }
            },
            {
              "ParameterName": "GlassColor",
              "ParameterValue": {
                "R": 0.027451,
                "G": 0.0,
                "B": 0.160784,
                "A": 1.0,
                "Hex": "2E0070"
              }
            },
            {
              "ParameterName": "BoosterColor",
              "ParameterValue": {
                "R": 0.278894,
                "G": 0.0,
                "B": 0.679542,
                "A": 1.0,
                "Hex": "9000D7"
              }
            },
            {
              "ParameterName": "AuxiliaryColor",
              "ParameterValue": {
                "R": 0.502886,
                "G": 0.061246,
                "B": 0.341914,
                "A": 1.0,
                "Hex": "BC469E"
              }
            }
          ]
        }
      },
      {
        "Key": {
          "TagName": "Cosmetics.Variant.Property.Vehicle.Painted.Saffron"
        },
        "Value": {
          "FloatParameters": [
            {
              "ParameterName": "ParticleColorVar",
              "ParameterValue": 5.0
            },
            {
              "ParameterName": "GlassColorVar",
              "ParameterValue": 0.1
            },
            {
              "ParameterName": "MinimumGlassColor",
              "ParameterValue": 2.0
            },
            {
              "ParameterName": "MaxGlassColor",
              "ParameterValue": 2.5
            }
          ],
          "IntParameters": [],
          "ColorParameters": [
            {
              "ParameterName": "PaintedColor",
              "ParameterValue": {
                "R": 0.1,
                "G": 0.1,
                "B": 0.00382,
                "A": 1.0,
                "Hex": "59590C"
              }
            },
            {
              "ParameterName": "GlowColor",
              "ParameterValue": {
                "R": 0.125,
                "G": 0.120959,
                "B": 0.015625,
                "A": 1.0,
                "Hex": "636121"
              }
            },
            {
              "ParameterName": "CoreColor",
              "ParameterValue": {
                "R": 0.896269,
                "G": 0.863157,
                "B": 0.0,
                "A": 1.0,
                "Hex": "F3EF00"
              }
            },
            {
              "ParameterName": "GlassColor",
              "ParameterValue": {
                "R": 0.527115,
                "G": 0.520996,
                "B": 0.016807,
                "A": 1.0,
                "Hex": "C0BF23"
              }
            },
            {
              "ParameterName": "BoosterColor",
              "ParameterValue": {
                "R": 0.896269,
                "G": 0.686685,
                "B": 0.0,
                "A": 1.0,
                "Hex": "F3D800"
              }
            },
            {
              "ParameterName": "AuxiliaryColor",
              "ParameterValue": {
                "R": 0.896269,
                "G": 0.686685,
                "B": 0.0,
                "A": 1.0,
                "Hex": "F3D800"
              }
            }
          ]
        }
      },
      {
        "Key": {
          "TagName": "Cosmetics.Variant.Property.Vehicle.Painted.SkyBlue"
        },
        "Value": {
          "FloatParameters": [
            {
              "ParameterName": "ParticleColorVar",
              "ParameterValue": 5.0
            },
            {
              "ParameterName": "GlassColorVar",
              "ParameterValue": 0.1
            },
            {
              "ParameterName": "MinimumGlassColor",
              "ParameterValue": 3.5
            }
          ],
          "IntParameters": [],
          "ColorParameters": [
            {
              "ParameterName": "PaintedColor",
              "ParameterValue": {
                "R": 0.020833,
                "G": 0.100565,
                "B": 0.2,
                "A": 1.0,
                "Hex": "27597C"
              }
            },
            {
              "ParameterName": "GlowColor",
              "ParameterValue": {
                "R": 0.055501,
                "G": 0.133276,
                "B": 0.171875,
                "A": 1.0,
                "Hex": "426673"
              }
            },
            {
              "ParameterName": "CoreColor",
              "ParameterValue": {
                "R": 0.333252,
                "G": 0.768412,
                "B": 0.984375,
                "A": 1.0,
                "Hex": "9CE3FE"
              }
            },
            {
              "ParameterName": "GlassColor",
              "ParameterValue": {
                "R": 0.013293,
                "G": 0.174976,
                "B": 0.374,
                "A": 1.0,
                "Hex": "1E74A5"
              }
            },
            {
              "ParameterName": "BoosterColor",
              "ParameterValue": {
                "R": 0.0,
                "G": 0.3564,
                "B": 0.533276,
                "A": 1.0,
                "Hex": "00A1C1"
              }
            },
            {
              "ParameterName": "AuxiliaryColor",
              "ParameterValue": {
                "R": 0.0,
                "G": 0.3564,
                "B": 0.533276,
                "A": 1.0,
                "Hex": "00A1C1"
              }
            }
          ]
        }
      },
      {
        "Key": {
          "TagName": "Cosmetics.Variant.Property.Vehicle.Painted.TitaniumWhite"
        },
        "Value": {
          "FloatParameters": [
            {
              "ParameterName": "ParticleColorVar",
              "ParameterValue": 5.0
            },
            {
              "ParameterName": "GlassColorVar",
              "ParameterValue": 0.1
            },
            {
              "ParameterName": "MinimumGlassColor",
              "ParameterValue": 1.5
            }
          ],
          "IntParameters": [],
          "ColorParameters": [
            {
              "ParameterName": "PaintedColor",
              "ParameterValue": {
                "R": 0.739583,
                "G": 0.739583,
                "B": 0.739583,
                "A": 1.0,
                "Hex": "E0E0E0"
              }
            },
            {
              "ParameterName": "GlowColor",
              "ParameterValue": {
                "R": 0.1875,
                "G": 0.1875,
                "B": 0.1875,
                "A": 1.0,
                "Hex": "787878"
              }
            },
            {
              "ParameterName": "CoreColor",
              "ParameterValue": {
                "R": 0.7,
                "G": 0.7,
                "B": 0.7,
                "A": 2.0,
                "Hex": "DADADA"
              }
            },
            {
              "ParameterName": "GlassColor",
              "ParameterValue": {
                "R": 0.546875,
                "G": 0.546875,
                "B": 0.546875,
                "A": 1.0,
                "Hex": "C3C3C3"
              }
            },
            {
              "ParameterName": "BoosterColor",
              "ParameterValue": {
                "R": 1.0,
                "G": 1.0,
                "B": 1.0,
                "A": 1.0,
                "Hex": "FFFFFF"
              }
            },
            {
              "ParameterName": "AuxiliaryColor",
              "ParameterValue": {
                "R": 0.7,
                "G": 0.7,
                "B": 0.7,
                "A": 1.0,
                "Hex": "DADADA"
              }
            }
          ]
        }
      }
    ],
    "CheatNames": [
      "HoloGlass"
    ],
    "MeshSchemaTag": {
      "TagName": "VehicleCosmetics.DriftTrail.HoloGlass"
    }
  }
}