{
  "Type": "FortGameFeatureData",
  "Name": "BlastBerryLoot",
  "Class": "UScriptClass'FortGameFeatureData'",
  "Flags": "RF_Public | RF_Standalone | RF_Transactional | RF_WasLoaded | RF_LoadCompleted",
  "Properties": {
    "LevelOverlayConfig": {
      "AssetPathName": "/BlastBerryLoot/Levels/BlastBerryLoot_LevelOverlay.BlastBerryLoot_LevelOverlay",
      "SubPathString": ""
    },
    "GameplayCueNotifyPaths": [
      "GameplayCues"
    ],
    "PlaylistBaseCurveTableOverrides": [
      {
        "BaseTable": {
          "AssetPathName": "/BlastBerryLoot/DataTables/BlastBerryGameDataSupplyDrop.BlastBerryGameDataSupplyDrop",
          "SubPathString": ""
        },
        "PlaylistToOverrideTableMap": [
          {
            "Key": {
              "TagName": "Athena.Playlist.BlastBerry.NoBuildSquad"
            },
            "Value": {
              "AssetPathName": "/BlastBerryLoot/DataTables/NoBuild/BlastBerryGameDataSupplyDrop_NoBuild.BlastBerryGameDataSupplyDrop_NoBuild",
              "SubPathString": ""
            }
          },
          {
            "Key": {
              "TagName": "Athena.Playlist.BlastBerry.Duo"
            },
            "Value": {
              "AssetPathName": "/BlastBerryLoot/DataTables/Duos/BlastBerryDuosGameDataSupplyDrop.BlastBerryDuosGameDataSupplyDrop",
              "SubPathString": ""
            }
          },
          {
            "Key": {
              "TagName": "Athena.Playlist.BlastBerry.NoBuildDuo"
            },
            "Value": {
              "AssetPathName": "/BlastBerryLoot/DataTables/Duos/NoBuild/BlastBerryGameDataSupplyDrop_DuosNoBuild.BlastBerryGameDataSupplyDrop_DuosNoBuild",
              "SubPathString": ""
            }
          },
          {
            "Key": {
              "TagName": "Athena.Playlist.BlastBerry.NoBuildTrio"
            },
            "Value": {
              "AssetPathName": "/BlastBerryLoot/DataTables/Trios/NoBuild/BlastBerryGameDataSupplyDrop_TriosNoBuild.BlastBerryGameDataSupplyDrop_TriosNoBuild",
              "SubPathString": ""
            }
          },
          {
            "Key": {
              "TagName": "Athena.Playlist.BlastBerry.Trio"
            },
            "Value": {
              "AssetPathName": "/BlastBerryLoot/DataTables/Trios/BlastBerryTriosGameDataSupplyDrop.BlastBerryTriosGameDataSupplyDrop",
              "SubPathString": ""
            }
          },
          {
            "Key": {
              "TagName": "Athena.Playlist.BlastBerry.Solo"
            },
            "Value": {
              "AssetPathName": "/BlastBerryLoot/DataTables/Solo/BlastBerrySoloGameDataSupplyDrop.BlastBerrySoloGameDataSupplyDrop",
              "SubPathString": ""
            }
          },
          {
            "Key": {
              "TagName": "Athena.Playlist.BlastBerry.NoBuildSolo"
            },
            "Value": {
              "AssetPathName": "/BlastBerryLoot/DataTables/Solo/NoBuild/BlastBerryGameDataSupplyDrop_SoloNoBuild.BlastBerryGameDataSupplyDrop_SoloNoBuild",
              "SubPathString": ""
            }
          }
        ]
      },
      {
        "BaseTable": {
          "AssetPathName": "/BlastBerryLoot/DataTables/BlastBerryGameDataHF.BlastBerryGameDataHF",
          "SubPathString": ""
        },
        "PlaylistToOverrideTableMap": [
          {
            "Key": {
              "TagName": "Athena.Playlist.BlastBerry.Duo"
            },
            "Value": {
              "AssetPathName": "/BlastBerryLoot/DataTables/Duos/BlastBerryDuosGameDataHF.BlastBerryDuosGameDataHF",
              "SubPathString": ""
            }
          },
          {
            "Key": {
              "TagName": "Athena.Playlist.BlastBerry.NoBuildDuo"
            },
            "Value": {
              "AssetPathName": "/BlastBerryLoot/DataTables/Duos/BlastBerryDuosGameDataHF.BlastBerryDuosGameDataHF",
              "SubPathString": ""
            }
          },
          {
            "Key": {
              "TagName": "Athena.Playlist.BlastBerry.NoBuildTrio"
            },
            "Value": {
              "AssetPathName": "/BlastBerryLoot/DataTables/Trios/BlastBerryTriosGameDataHF.BlastBerryTriosGameDataHF",
              "SubPathString": ""
            }
          },
          {
            "Key": {
              "TagName": "Athena.Playlist.BlastBerry.Trio"
            },
            "Value": {
              "AssetPathName": "/BlastBerryLoot/DataTables/Trios/BlastBerryTriosGameDataHF.BlastBerryTriosGameDataHF",
              "SubPathString": ""
            }
          },
          {
            "Key": {
              "TagName": "Athena.Playlist.BlastBerry.Solo"
            },
            "Value": {
              "AssetPathName": "/BlastBerryLoot/DataTables/Solo/BlastBerrySoloGameDataHF.BlastBerrySoloGameDataHF",
              "SubPathString": ""
            }
          },
          {
            "Key": {
              "TagName": "Athena.Playlist.BlastBerry.NoBuildSolo"
            },
            "Value": {
              "AssetPathName": "/BlastBerryLoot/DataTables/Solo/BlastBerrySoloGameDataHF.BlastBerrySoloGameDataHF",
              "SubPathString": ""
            }
          },
          {
            "Key": {
              "TagName": "Athena.Playlist.BlastBerry.SoloTest"
            },
            "Value": {
              "AssetPathName": "/BlastBerryLoot/DataTables/Solo/BlastBerrySoloGameDataHF2.BlastBerrySoloGameDataHF2",
              "SubPathString": ""
            }
          },
          {
            "Key": {
              "TagName": "Athena.Playlist.BlastBerry.Squad"
            },
            "Value": {
              "AssetPathName": "/BlastBerryLoot/DataTables/Squad/BlastBerrySquadGameDataHF.BlastBerrySquadGameDataHF",
              "SubPathString": ""
            }
          },
          {
            "Key": {
              "TagName": "Athena.Playlist.BlastBerry.NoBuildSquad"
            },
            "Value": {
              "AssetPathName": "/BlastBerryLoot/DataTables/Squad/BlastBerrySquadGameDataHF.BlastBerrySquadGameDataHF",
              "SubPathString": ""
            }
          }
        ]
      },
      {
        "BaseTable": {
          "AssetPathName": "/DragonCartWads/DataTables/DragonCartWadsGameData.DragonCartWadsGameData",
          "SubPathString": ""
        },
        "PlaylistToOverrideTableMap": [
          {
            "Key": {
              "TagName": "Athena.Playlist.BlastBerry"
            },
            "Value": {
              "AssetPathName": "/BlastBerryLoot/DataTables/BlastBerry_DragonCartWadsGameData.BlastBerry_DragonCartWadsGameData",
              "SubPathString": ""
            }
          }
        ]
      },
      {
        "BaseTable": {
          "AssetPathName": "/Game/Athena/Balance/DataTables/CashPricingItemDef.CashPricingItemDef",
          "SubPathString": ""
        },
        "PlaylistToOverrideTableMap": [
          {
            "Key": {
              "TagName": "Plugin.Playlist.BlastBerry"
            },
            "Value": {
              "AssetPathName": "/BlastBerryLoot/DataTables/CashPricingItemDef_Composite_BB.CashPricingItemDef_Composite_BB",
              "SubPathString": ""
            }
          }
        ]
      }
    ],
    "PlaylistBaseDataTableOverrides": [
      {
        "BaseTable": {
          "AssetPathName": "/Game/Athena/Balance/Movement/MovementOverrides/Ch5/DataTables/Ch5CharacterAttributes.Ch5CharacterAttributes",
          "SubPathString": ""
        },
        "PlaylistToOverrideTableMap": [
          {
            "Key": {
              "TagName": "Plugin.Playlist.BlastBerry"
            },
            "Value": {
              "AssetPathName": "/BlastBerryLoot/DataTables/BlastBerryCharacterAttributes.BlastBerryCharacterAttributes",
              "SubPathString": ""
            }
          }
        ]
      },
      {
        "BaseTable": {
          "AssetPathName": "/Game/Balance/DataTables/UtilityItemDamage.UtilityItemDamage",
          "SubPathString": ""
        },
        "PlaylistToOverrideTableMap": [
          {
            "Key": {
              "TagName": "Plugin.Playlist.BlastBerry"
            },
            "Value": {
              "AssetPathName": "/BlastBerryLoot/DataTables/BlastBerry_UtilityItemDamage.BlastBerry_UtilityItemDamage",
              "SubPathString": ""
            }
          }
        ]
      }
    ],
    "Actions": [
      {
        "ObjectName": "UFortGameFeatureAction_LootTierGroups'BlastBerryLoot:UFortGameFeatureAction_LootTierGroups_0'",
        "ObjectPath": "/BlastBerryLoot/BlastBerryLoot.2"
      },
      {
        "ObjectName": "FortGameFeatureAction_AddToPlaylists'BlastBerryLoot:FortGameFeatureAction_AddToPlaylists_0'",
        "ObjectPath": "/BlastBerryLoot/BlastBerryLoot.0"
      }
    ]
  }
}