{
  "Type": "AthenaSprayItemDefinition",
  "Name": "Spray_Tournament_YB",
  "Flags": "RF_Public | RF_Standalone | RF_Transactional | RF_WasLoaded | RF_LoadCompleted",
  "Class": "UScriptClass'AthenaSprayItemDefinition'",
  "Package": "/BRCosmetics/Athena/Items/Cosmetics/Sprays/Spray_Tournament_YB",
  "Properties": {
    "DecalMaterial": {
      "AssetPathName": "/Game/Athena/Cosmetics/Sprays/MI_SprayDecal_Standard.MI_SprayDecal_Standard",
      "SubPathString": ""
    },
    "DecalTexture": {
      "AssetPathName": "/BRCosmetics/2dAssets/Sprays/Season25/Textures/T-Sprays-Season25-S25-Tournament-YB.T-Sprays-Season25-S25-Tournament-YB",
      "SubPathString": ""
    },
    "ItemName": {
      "Namespace": "",
      "Key": "EB418BDD4CBF526554E0678B8601EB34",
      "SourceString": "Yuji's Training",
      "LocalizedString": "Yuji's Training"
    },
    "ItemDescription": {
      "Namespace": "",
      "Key": "D2708211443035D80E57A4AEC6D1C626",
      "SourceString": "Leave your mark. ",
      "LocalizedString": "Leave your mark. "
    },
    "ItemShortDescription": {
      "Namespace": "",
      "Key": "548FEC10446716CC19C676A77B750792",
      "SourceString": "Spray",
      "LocalizedString": "Spray"
    },
    "DataList": [
      {
        "MinLevel": 1,
        "MaxLevel": 1
      },
      {
        "Traits": [
          "Item.Trait.SingleStack"
        ]
      },
      {
        "Tags": [
          "Cosmetics.EmoteType.Spray",
          "Cosmetics.Filter.Season.25",
          "Cosmetics.Set.CleanWard"
        ]
      },
      {
        "Icon": {
          "AssetPathName": "/BRCosmetics/2dAssets/Sprays/Season25/PreviewImages/T-T-Sprays-Season25-PreviewImages-S25-Tournament-YB.T-T-Sprays-Season25-PreviewImages-S25-Tournament-YB",
          "SubPathString": ""
        }
      },
      {
        "GeneratedTagsIndexes": [
          244,
          553,
          556,
          565,
          126,
          269,
          1,
          55,
          640,
          252,
          124,
          663,
          675,
          292,
          42,
          740,
          1083,
          435,
          1677,
          2869,
          2941,
          5041
        ]
      }
    ]
  }
}