{
  "Type": "AthenaSprayItemDefinition",
  "Name": "Spray_SacredCuddle",
  "Flags": "RF_Public | RF_Standalone | RF_Transactional | RF_WasLoaded | RF_LoadCompleted",
  "Class": "UScriptClass'AthenaSprayItemDefinition'",
  "Package": "/BRCosmetics/Athena/Items/Cosmetics/Sprays/Spray_SacredCuddle",
  "Properties": {
    "DecalMaterial": {
      "AssetPathName": "/Game/Athena/Cosmetics/Sprays/MI_SprayDecal_Standard.MI_SprayDecal_Standard",
      "SubPathString": ""
    },
    "DecalTexture": {
      "AssetPathName": "/BRCosmetics/2dAssets/Sprays/Season33/Textures/TSpraysS33SacredCuddle.TSpraysS33SacredCuddle",
      "SubPathString": ""
    },
    "ItemName": {
      "Namespace": "",
      "Key": "66A2BBBC451B02B4B04D2CBEE44B0651",
      "SourceString": "Eyes of the Cuddle Team",
      "LocalizedString": "Eyes of the Cuddle Team"
    },
    "ItemDescription": {
      "Namespace": "",
      "Key": "6BC9B47E4E381D9FB6C9D99598699434",
      "SourceString": "Leave your mark.",
      "LocalizedString": "Leave your mark."
    },
    "ItemShortDescription": {
      "Namespace": "",
      "Key": "1EA955DA4B9638C8C6C4D3979607506C",
      "SourceString": "Spray",
      "LocalizedString": "Spray"
    },
    "DataList": [
      {
        "MinLevel": 1,
        "MaxLevel": 1
      },
      {
        "Traits": [
          "Item.Trait.SingleStack"
        ]
      },
      {
        "Tags": [
          "Cosmetics.EmoteType.Spray",
          "Cosmetics.Filter.Season.33",
          "Cosmetics.Set.LoveSight"
        ]
      },
      {
        "Icon": {
          "AssetPathName": "/BRCosmetics/2dAssets/Sprays/Season33/PreviewImages/TSpraysPreviewImagesS33SacredCuddle.TSpraysPreviewImagesS33SacredCuddle",
          "SubPathString": ""
        }
      },
      {
        "LargeIcon": {
          "AssetPathName": "/BRCosmetics/2dAssets/Sprays/Season33/PreviewImages/TSpraysPreviewImagesS33SacredCuddleL.TSpraysPreviewImagesS33SacredCuddleL",
          "SubPathString": ""
        }
      },
      {
        "GeneratedTagsIndexes": [
          244,
          557,
          367,
          254,
          167,
          577,
          302,
          108,
          28,
          641,
          652,
          292,
          778,
          948,
          1009,
          435,
          48,
          148,
          1594,
          1693,
          2883
        ]
      }
    ]
  }
}