{
  "Type": "FortCosmeticMaterialVariant",
  "Name": "FortCosmeticMaterialVariant_0",
  "Flags": "RF_Public | RF_Transactional | RF_WasLoaded | RF_LoadCompleted",
  "Class": "UScriptClass'FortCosmeticMaterialVariant'",
  "Outer": {
    "ObjectName": "AthenaCharacterItemDefinition'Character_RosyChuckle'",
    "ObjectPath": "/BRCosmetics/Athena/Items/Cosmetics/Characters/Character_RosyChuckle.0"
  },
  "Properties": {
    "MaterialOptions": [
      {
        "VariantMaterials": [],
        "VariantMaterialParams": [],
        "VariantSounds": [],
        "VariantFoley": [],
        "CosmeticProperties": [],
        "MetaTags": {
          "MetaTagsToApply": [],
          "MetaTagsToRemove": []
        },
        "bStartUnlocked": false,
        "bIsDefault": true,
        "bHideIfNotOwned": false,
        "CustomizationVariantTag": {
          "TagName": "Cosmetics.Variant.Property.Stage1"
        },
        "VariantName": {
          "Namespace": "",
          "Key": "82D5884E4F9CC01DFCECF98BCE8AE1CF",
          "SourceString": "Lt. Winter",
          "LocalizedString": "Lt. Winter"
        },
        "PreviewImage": {
          "AssetPathName": "/BRCosmetics/UI/Foundation/Textures/Icons/Heroes/Athena/Soldier/S39/T_Soldier_RosyChuckle.T_Soldier_RosyChuckle",
          "SubPathString": ""
        },
        "UnlockRequirements": {
          "CultureInvariantString": null
        },
        "UnlockingItemDef": {
          "AssetPathName": "",
          "SubPathString": ""
        },
        "VariantGameplayTags": []
      },
      {
        "VariantMaterials": [
          {
            "MaterialToSwap": {
              "AssetPathName": "/BRCosmetics/Characters/Player/Male/Medium/Bodies/M_MED_RosyChuckle/Materials/MI_RosyChuckle_Body.MI_RosyChuckle_Body",
              "SubPathString": ""
            },
            "ComponentToOverride": "None",
            "CascadeMaterialName": "None",
            "MaterialOverrideIndex": 0,
            "OverrideMaterial": {
              "AssetPathName": "/BRCosmetics/Characters/Player/Male/Medium/Bodies/M_MED_RosyChuckle/Skins/Fork/Materials/MI_RosyChuckle_Fork_Body.MI_RosyChuckle_Fork_Body",
              "SubPathString": ""
            }
          },
          {
            "MaterialToSwap": {
              "AssetPathName": "/BRCosmetics/Characters/Player/Male/Medium/Bodies/M_MED_RosyChuckle/Materials/MI_RosyChuckle_FaceAcc.MI_RosyChuckle_FaceAcc",
              "SubPathString": ""
            },
            "ComponentToOverride": "None",
            "CascadeMaterialName": "None",
            "MaterialOverrideIndex": 0,
            "OverrideMaterial": {
              "AssetPathName": "/BRCosmetics/Characters/Player/Male/Medium/Bodies/M_MED_RosyChuckle/Skins/Fork/Materials/MI_RosyChuckle_Fork_FaceAcc.MI_RosyChuckle_Fork_FaceAcc",
              "SubPathString": ""
            }
          },
          {
            "MaterialToSwap": {
              "AssetPathName": "/BRCosmetics/Characters/Player/Male/Medium/Bodies/M_MED_RosyChuckle/Materials/MI_RosyChuckle_Glass.MI_RosyChuckle_Glass",
              "SubPathString": ""
            },
            "ComponentToOverride": "None",
            "CascadeMaterialName": "None",
            "MaterialOverrideIndex": 0,
            "OverrideMaterial": {
              "AssetPathName": "/BRCosmetics/Characters/Player/Male/Medium/Bodies/M_MED_RosyChuckle/Skins/Fork/Materials/MI_RosyChuckle_Fork_Glass.MI_RosyChuckle_Fork_Glass",
              "SubPathString": ""
            }
          }
        ],
        "VariantMaterialParams": [],
        "VariantSounds": [],
        "VariantFoley": [],
        "CosmeticProperties": [
          {
            "OverrideMaterialParams": null,
            "AdditionalScalarParameters": [],
            "AdditionalVectorParameters": [
              {
                "ParameterInfo": {
                  "Name": "SockPrimaryColor",
                  "Association": "EMaterialParameterAssociation::GlobalParameter",
                  "Index": -1
                },
                "ParameterValue": {
                  "R": 0.252221,
                  "G": 0.257848,
                  "B": 0.272569,
                  "A": 1.0,
                  "Hex": "8A8B8F"
                },
                "ExpressionGUID": "00000000-00000000-00000000-00000000"
              }
            ],
            "AdditionalTextureParameters": [],
            "bApplyToOverlayMaterial": false,
            "bCombineMaterialParams": false,
            "bAttemptVariantInfoTransfer": false,
            "MaterialParameterNameForVariantInfo": "None",
            "PropertyTag": {
              "TagName": "CosmeticProperty.MorphOverrideData"
            }
          }
        ],
        "MetaTags": {
          "MetaTagsToApply": [],
          "MetaTagsToRemove": []
        },
        "bStartUnlocked": false,
        "bIsDefault": false,
        "bHideIfNotOwned": false,
        "CustomizationVariantTag": {
          "TagName": "Cosmetics.Variant.Property.Stage2"
        },
        "VariantName": {
          "Namespace": "",
          "Key": "D5035D7A4995548088B5E585A5499E83",
          "SourceString": "Winterwish Lt. Winter",
          "LocalizedString": "Winterwish Lt. Winter"
        },
        "PreviewImage": {
          "AssetPathName": "/BRCosmetics/UI/Foundation/Textures/Icons/Heroes/Athena/Soldier/S39/T_Soldier_RosyChuckle_Fork.T_Soldier_RosyChuckle_Fork",
          "SubPathString": ""
        },
        "UnlockRequirements": {
          "CultureInvariantString": null
        },
        "UnlockingItemDef": {
          "AssetPathName": "",
          "SubPathString": ""
        },
        "VariantGameplayTags": []
      }
    ],
    "VariantChannelName": {
      "Namespace": "",
      "Key": "C155F9C94F7499DC0D51099CFDE8C052",
      "SourceString": "Style",
      "LocalizedString": "Style"
    },
    "VariantChannelTag": {
      "TagName": "Cosmetics.Variant.Channel.Progressive"
    }
  }
}