{
  "Type": "FortQuestDefinitionComponent_DisplaySettings",
  "Name": "FortQuestDefinitionComponent_DisplaySettings_0",
  "Outer": "Phoenix_ReactiveKill_Quest_B8",
  "Class": "UScriptClass'FortQuestDefinitionComponent_DisplaySettings'",
  "Flags": "RF_Transactional | RF_WasLoaded | RF_LoadCompleted",
  "Properties": {
    "InformationSettings": {
      "CompletionText": {
        "Namespace": "",
        "Key": "405CA3F942A1A6226DAEEEBFA7FCA7DC",
        "SourceString": "Mist Monsters Eliminated!",
        "LocalizedString": "Mist Monsters Eliminated!"
      }
    }
  }
}