{
  "Type": "FortRiftAnomaliesData",
  "Name": "RA_StormFocus_DA",
  "Flags": "RF_Public | RF_Standalone | RF_Transactional | RF_WasLoaded | RF_LoadCompleted",
  "Class": "UScriptClass'FortRiftAnomaliesData'",
  "Package": "/RA_StormFocus/Gameplay/RA_StormFocus_DA",
  "Properties": {
    "RAName": {
      "Namespace": "",
      "Key": "688D1967460D0841F8185EB9677CDDAF",
      "SourceString": "Storm Focus",
      "LocalizedString": "Storm Focus"
    },
    "RADescription": {
      "Namespace": "",
      "Key": "EEADE4694EDBF6A47683328C271F596B",
      "SourceString": "The Rift has chosen the final location for the storm! It's been marked on the map!",
      "LocalizedString": "The Rift has chosen the final location for the storm! It's been marked on the map!"
    },
    "RAShortDescription": {
      "Namespace": "",
      "Key": "3A5A309B4DE4C33CD37DF1838B7A9A70",
      "SourceString": "The Rift has chosen the final location for the storm!",
      "LocalizedString": "The Rift has chosen the final location for the storm!"
    },
    "RAMarkerSound": {
      "AssetPathName": "/RA_StormFocus/Assets/Audio/SC_Fort_UI_Sight_BigPositive_03.SC_Fort_UI_Sight_BigPositive_03",
      "SubPathString": ""
    },
    "EQSToUSe": {
      "AssetPathName": "/RiftAnomaliesGameplay/Gameplay/EQS/EQS_MMF.EQS_MMF",
      "SubPathString": ""
    },
    "PersistentRiftAnomalieClass": {
      "AssetPathName": "/RA_StormFocus/Gameplay/B_RA_StormFocus.B_RA_StormFocus_C",
      "SubPathString": ""
    }
  }
}