{
  "Type": "AssembledMeshSchema",
  "Name": "AMS_Figure_BunnyB",
  "Class": "UScriptClass'AssembledMeshSchema'",
  "Flags": "RF_Public | RF_Standalone | RF_Transactional | RF_WasLoaded | RF_LoadCompleted",
  "Properties": {
    "CustomizableObjectInstance": {
      "AssetPathName": "/FigureCosmetics/Figure/Figure_BunnyB/Mutable/COI_Figure_BunnyB.COI_Figure_BunnyB",
      "SubPathString": ""
    },
    "AdditionalData": [
      {
        "WidePreviewImage": {
          "AssetPathName": "",
          "SubPathString": ""
        },
        "SmallPreviewImage": {
          "AssetPathName": "/FigureCosmetics/UI/Icons/Figure/Season29/Icons/T-UI-Icon-Figure-BunnyB.T-UI-Icon-Figure-BunnyB",
          "SubPathString": ""
        },
        "LargePreviewImage": {
          "AssetPathName": "/FigureCosmetics/UI/Icons/Figure/Season29/Icons/T-UI-Icon-Figure-BunnyB-L.T-UI-Icon-Figure-BunnyB-L",
          "SubPathString": ""
        },
        "FullScreenImage": {
          "AssetPathName": "",
          "SubPathString": ""
        }
      }
    ]
  }
}