{
  "Type": "FortMtxOfferData",
  "Name": "DA_Featured_Pickle_Bundle",
  "Flags": "RF_Public | RF_Standalone | RF_Transactional | RF_WasLoaded | RF_LoadCompleted",
  "Class": "UScriptClass'FortMtxOfferData'",
  "Package": "/OfferCatalog/DisplayAssets/DA_Featured_Pickle_Bundle",
  "Properties": {
    "DisplayName": {
      "Namespace": "",
      "Key": "46C8976B4ABC1B189601029CCA0FC08E",
      "SourceString": "Void Burn",
      "LocalizedString": "Void Burn"
    },
    "TileImageSize": {
      "X": 1024.0,
      "Y": 1024.0
    },
    "BadgeImageSize": {
      "X": 32.0,
      "Y": 32.0
    },
    "DetailsImageSize": {
      "X": 1024.0,
      "Y": 1024.0
    },
    "SimpleImageSize": {
      "X": 32.0,
      "Y": 32.0
    },
    "DetailsAttributes": [
      {
        "Name": {
          "Namespace": "",
          "Key": "410ED0E84F6C4C2C991D9F8C0EB62FB4",
          "SourceString": "<text color=\"FFFFFFFF\">Double Agent Hush</> Outfit (includes additional style)",
          "LocalizedString": "<text color=\"FFFFFFFF\">Double Agent Hush</> Outfit (includes additional style)"
        },
        "Value": {
          "CultureInvariantString": null
        }
      },
      {
        "Name": {
          "Namespace": "",
          "Key": "F94C21C9445ACACFE04B0197F69C0370",
          "SourceString": "<text color=\"FFFFFFFF\">Double Agent Stripe</> Back Bling",
          "LocalizedString": "<text color=\"FFFFFFFF\">Double Agent Stripe</> Back Bling"
        },
        "Value": {
          "CultureInvariantString": null
        }
      },
      {
        "Name": {
          "Namespace": "",
          "Key": "9248617C4961481575CB1BB58297E3CD",
          "SourceString": "<text color=\"FFFFFFFF\">Double Agent Wildcard</> Outfit (includes additional style)",
          "LocalizedString": "<text color=\"FFFFFFFF\">Double Agent Wildcard</> Outfit (includes additional style)"
        },
        "Value": {
          "CultureInvariantString": null
        }
      },
      {
        "Name": {
          "Namespace": "",
          "Key": "728592984FDF54A257CA8D872AA810BF",
          "SourceString": "<text color=\"FFFFFFFF\">Double Agent Hard Case</> Back Bling",
          "LocalizedString": "<text color=\"FFFFFFFF\">Double Agent Hard Case</> Back Bling"
        },
        "Value": {
          "CultureInvariantString": null
        }
      },
      {
        "Name": {
          "Namespace": "",
          "Key": "3FF5C2AC407573D7D8E2A4A4C929B085",
          "SourceString": "<text color=\"FFFFFFFF\">Chaos Double Agent</> Outfit (includes additional style)",
          "LocalizedString": "<text color=\"FFFFFFFF\">Chaos Double Agent</> Outfit (includes additional style)"
        },
        "Value": {
          "CultureInvariantString": null
        }
      },
      {
        "Name": {
          "Namespace": "",
          "Key": "D4B033B04111CFF4FAFF52A35B71C913",
          "SourceString": "<text color=\"FFFFFFFF\">Double Agent Ooze Unit</> Back Bling",
          "LocalizedString": "<text color=\"FFFFFFFF\">Double Agent Ooze Unit</> Back Bling"
        },
        "Value": {
          "CultureInvariantString": null
        }
      }
    ],
    "BackgroundImageSize": {
      "X": 32.0,
      "Y": 32.0
    },
    "DisplaySize": "EFortMtxOfferDisplaySize::Large"
  }
}