{
  "Type": "PlaylistUserOptionIntEnum",
  "Name": "Device_Mannequin_EmoteIndex_UserOption",
  "Class": "UScriptClass'PlaylistUserOptionIntEnum'",
  "Flags": "RF_Public | RF_Standalone | RF_Transactional | RF_WasLoaded | RF_LoadCompleted",
  "Properties": {
    "OptionValues": [
      {
        "Value": 3,
        "DisplayName": {
          "Namespace": "",
          "Key": "547F9ECE433F5DCC51DC8C8A1B65CFF2",
          "SourceString": "Beckon",
          "LocalizedString": "Beckon"
        },
        "OptionValueName": "Beckon",
        "GrantedContextTags": [],
        "OptionalDisplayIcon": {
          "SmallIcon": {
            "AssetPathName": "",
            "SubPathString": ""
          },
          "LargeIcon": {
            "AssetPathName": "",
            "SubPathString": ""
          }
        }
      },
      {
        "Value": 4,
        "DisplayName": {
          "Namespace": "",
          "Key": "B6D2309C45AC085925C5CB9692FFAE17",
          "SourceString": "Air Horn",
          "LocalizedString": "Air Horn"
        },
        "OptionValueName": "AirHorn",
        "GrantedContextTags": [],
        "OptionalDisplayIcon": {
          "SmallIcon": {
            "AssetPathName": "",
            "SubPathString": ""
          },
          "LargeIcon": {
            "AssetPathName": "",
            "SubPathString": ""
          }
        }
      },
      {
        "Value": 5,
        "DisplayName": {
          "Namespace": "",
          "Key": "D85C9B2543C7D9988CD3F4AD751320F6",
          "SourceString": "Cheer",
          "LocalizedString": "Cheer"
        },
        "OptionValueName": "Cheer",
        "GrantedContextTags": [],
        "OptionalDisplayIcon": {
          "SmallIcon": {
            "AssetPathName": "",
            "SubPathString": ""
          },
          "LargeIcon": {
            "AssetPathName": "",
            "SubPathString": ""
          }
        }
      },
      {
        "Value": 6,
        "DisplayName": {
          "Namespace": "",
          "Key": "70CA75A24A9A175595EB7EA02A7E8F53",
          "SourceString": "Clap",
          "LocalizedString": "Clap"
        },
        "OptionValueName": "Clap",
        "GrantedContextTags": [],
        "OptionalDisplayIcon": {
          "SmallIcon": {
            "AssetPathName": "",
            "SubPathString": ""
          },
          "LargeIcon": {
            "AssetPathName": "",
            "SubPathString": ""
          }
        }
      },
      {
        "Value": 7,
        "DisplayName": {
          "Namespace": "",
          "Key": "6C2762B347B40BE32141678CBB5E9836",
          "SourceString": "Nod Head",
          "LocalizedString": "Nod Head"
        },
        "OptionValueName": "NodHead",
        "GrantedContextTags": [],
        "OptionalDisplayIcon": {
          "SmallIcon": {
            "AssetPathName": "",
            "SubPathString": ""
          },
          "LargeIcon": {
            "AssetPathName": "",
            "SubPathString": ""
          }
        }
      },
      {
        "Value": 8,
        "DisplayName": {
          "Namespace": "",
          "Key": "16F136C9405B2785A3ADFEA01BA90386",
          "SourceString": "Phone Wave",
          "LocalizedString": "Phone Wave"
        },
        "OptionValueName": "PhoneWave",
        "GrantedContextTags": [],
        "OptionalDisplayIcon": {
          "SmallIcon": {
            "AssetPathName": "",
            "SubPathString": ""
          },
          "LargeIcon": {
            "AssetPathName": "",
            "SubPathString": ""
          }
        }
      },
      {
        "Value": 9,
        "DisplayName": {
          "Namespace": "",
          "Key": "720F5A9C46A95CD35FC5C7AAC9D845B1",
          "SourceString": "Point",
          "LocalizedString": "Point"
        },
        "OptionValueName": "Point",
        "GrantedContextTags": [],
        "OptionalDisplayIcon": {
          "SmallIcon": {
            "AssetPathName": "",
            "SubPathString": ""
          },
          "LargeIcon": {
            "AssetPathName": "",
            "SubPathString": ""
          }
        }
      },
      {
        "Value": 10,
        "DisplayName": {
          "Namespace": "",
          "Key": "352D1B304AF9696393EBD6B821095C35",
          "SourceString": "Shake Head",
          "LocalizedString": "Shake Head"
        },
        "OptionValueName": "Shake Head",
        "GrantedContextTags": [],
        "OptionalDisplayIcon": {
          "SmallIcon": {
            "AssetPathName": "",
            "SubPathString": ""
          },
          "LargeIcon": {
            "AssetPathName": "",
            "SubPathString": ""
          }
        }
      },
      {
        "Value": 11,
        "DisplayName": {
          "Namespace": "",
          "Key": "9B0927B1464783A1EE75CFB1C659CEE5",
          "SourceString": "Wave",
          "LocalizedString": "Wave"
        },
        "OptionValueName": "Wave",
        "GrantedContextTags": [],
        "OptionalDisplayIcon": {
          "SmallIcon": {
            "AssetPathName": "",
            "SubPathString": ""
          },
          "LargeIcon": {
            "AssetPathName": "",
            "SubPathString": ""
          }
        }
      },
      {
        "Value": 0,
        "DisplayName": {
          "Namespace": "",
          "Key": "962936A24AA23E799A7EFEA176AA044F",
          "SourceString": "Sit In Chair",
          "LocalizedString": "Sit In Chair"
        },
        "OptionValueName": "SitInChair",
        "GrantedContextTags": [],
        "OptionalDisplayIcon": {
          "SmallIcon": {
            "AssetPathName": "",
            "SubPathString": ""
          },
          "LargeIcon": {
            "AssetPathName": "",
            "SubPathString": ""
          }
        }
      },
      {
        "Value": 2,
        "DisplayName": {
          "Namespace": "",
          "Key": "FE6AD84240087704D6CC50812EF95305",
          "SourceString": "Air Guitar",
          "LocalizedString": "Air Guitar"
        },
        "OptionValueName": "AirGuitar",
        "GrantedContextTags": [],
        "OptionalDisplayIcon": {
          "SmallIcon": {
            "AssetPathName": "",
            "SubPathString": ""
          },
          "LargeIcon": {
            "AssetPathName": "",
            "SubPathString": ""
          }
        }
      },
      {
        "Value": 1,
        "DisplayName": {
          "Namespace": "",
          "Key": "1DA6340B43D4C415D1A57DA527173771",
          "SourceString": "Ground Pound",
          "LocalizedString": "Ground Pound"
        },
        "OptionValueName": "AcrobaticSuperHero",
        "GrantedContextTags": [],
        "OptionalDisplayIcon": {
          "SmallIcon": {
            "AssetPathName": "",
            "SubPathString": ""
          },
          "LargeIcon": {
            "AssetPathName": "",
            "SubPathString": ""
          }
        }
      }
    ],
    "OptionKey": "EmoteIndex",
    "OptionDisplayName": {
      "Namespace": "",
      "Key": "98D2414B475754616443AEAACD1CA205",
      "SourceString": "Emote",
      "LocalizedString": "Emote"
    },
    "OptionDescription": {
      "Namespace": "",
      "Key": "9CF33CC74B72427C243E56BD9236C6A8",
      "SourceString": "Sets the emote that this character device plays when activated.",
      "LocalizedString": "Sets the emote that this character device plays when activated."
    },
    "Tags": [
      "Creative.Property.Basic"
    ]
  }
}