{
  "Type": "AthenaItemWrapDefinition",
  "Name": "Wrap_174_Cavalry",
  "Flags": "RF_Public | RF_Standalone | RF_Transactional | RF_WasLoaded | RF_LoadCompleted",
  "Class": "UScriptClass'AthenaItemWrapDefinition'",
  "Package": "/BRCosmetics/Athena/Items/Cosmetics/ItemWraps/Wrap_174_Cavalry",
  "Properties": {
    "ItemWrapMaterial": {
      "AssetPathName": "/BRCosmetics/Weapons/WeaponSkins/Wraps/Materials/MI_WeaponWrap_Cavalry.MI_WeaponWrap_Cavalry",
      "SubPathString": ""
    },
    "ItemName": {
      "Namespace": "",
      "Key": "891307FD45F57F23B1ACB690FD7DB126",
      "SourceString": "Weathered Black",
      "LocalizedString": "Weathered Black"
    },
    "ItemDescription": {
      "Namespace": "",
      "Key": "B3EE307E423FC9139356D38D50D2CDA8",
      "SourceString": "Show your style.",
      "LocalizedString": "Show your style."
    },
    "DataList": [
      {
        "MinLevel": 1,
        "MaxLevel": 1
      },
      {
        "Traits": [
          "Item.Trait.SingleStack"
        ]
      },
      {
        "Icon": {
          "AssetPathName": "/BRCosmetics/UI/Foundation/Textures/Icons/Wraps/T-Wraps-CavalryWrap.T-Wraps-CavalryWrap",
          "SubPathString": ""
        }
      },
      {
        "LargeIcon": {
          "AssetPathName": "/BRCosmetics/UI/Foundation/Textures/Icons/Wraps/T-Wraps-CavalryWrap-L.T-Wraps-CavalryWrap-L",
          "SubPathString": ""
        }
      },
      {
        "Tags": [
          "Cosmetics.Filter.Season.11",
          "Cosmetics.Source.ItemShop",
          "Cosmetics.Set.QuietWatcher"
        ]
      },
      {
        "GeneratedTagsIndexes": [
          244,
          557,
          367,
          254,
          171,
          27,
          665,
          714,
          68,
          184,
          906,
          176,
          1971,
          2190,
          418,
          525,
          3211,
          3574,
          4814,
          4807
        ]
      }
    ]
  }
}