{
  "Type": "AthenaBackpackItemDefinition",
  "Name": "BID_248_Pilots",
  "Flags": "RF_Public | RF_Standalone | RF_Transactional | RF_WasLoaded | RF_LoadCompleted",
  "Class": "UScriptClass'AthenaBackpackItemDefinition'",
  "Package": "/BRCosmetics/Athena/Items/Cosmetics/Backpacks/BID_248_Pilots",
  "Properties": {
    "CharacterParts": [
      {
        "ObjectName": "CustomCharacterPart'CP_Backpack_Pilots'",
        "ObjectPath": "/BRCosmetics/Characters/CharacterParts/Backpacks/CP_Backpack_Pilots.1"
      }
    ],
    "ObservedPlayerStats": [
      "StatManager.AthenaKills"
    ],
    "ItemPreviewHero": {
      "AssetPathName": "/BRCosmetics/Athena/Items/Cosmetics/Characters/CID_385_Athena_Commando_M_PilotSkull.CID_385_Athena_Commando_M_PilotSkull",
      "SubPathString": ""
    },
    "ItemName": {
      "Namespace": "",
      "Key": "C650CB194167CF74DAFA2E891CCF3095",
      "SourceString": "Gauge",
      "LocalizedString": "Gauge"
    },
    "ItemDescription": {
      "Namespace": "",
      "Key": "ABD8E384419BEBF3CF95B391E123FE8F",
      "SourceString": "Targets engaged.\r\nReactive: Displays your number of eliminations in the match.",
      "LocalizedString": "Targets engaged.\r\nReactive: Displays your number of eliminations in the match."
    },
    "ItemShortDescription": {
      "Namespace": "",
      "Key": "22508A4C4313DD226BDDD7AA32C3BA82",
      "SourceString": "Back Bling",
      "LocalizedString": "Back Bling"
    },
    "DataList": [
      {
        "MinLevel": 1,
        "MaxLevel": 1
      },
      {
        "Traits": [
          "Item.Trait.SingleStack"
        ]
      },
      {
        "Icon": {
          "AssetPathName": "/BRCosmetics/UI/Foundation/Textures/Icons/Backpacks/T-Icon-Backpacks-248-Pilots.T-Icon-Backpacks-248-Pilots",
          "SubPathString": ""
        }
      },
      {
        "LargeIcon": {
          "AssetPathName": "/BRCosmetics/UI/Foundation/Textures/Icons/Backpacks/T-Icon-Backpacks-248-Pilots-L.T-Icon-Backpacks-248-Pilots-L",
          "SubPathString": ""
        }
      },
      {
        "Tags": [
          "Cosmetics.Set.Pilots",
          "Cosmetics.Source.ItemShop",
          "Cosmetics.UserFacingFlags.Reactive",
          "Cosmetics.Filter.Season.8"
        ]
      },
      {
        "GeneratedTagsIndexes": [
          9,
          244,
          551,
          367,
          254,
          167,
          577,
          581,
          171,
          47,
          283,
          41,
          737,
          174,
          895,
          1030,
          453,
          1161,
          1303,
          325,
          1857,
          445,
          2521,
          2523,
          2524,
          2530,
          2610,
          2689,
          2705,
          3182,
          3360
        ]
      },
      {
        "Rarity": "EFortRarity::Legendary"
      }
    ]
  }
}