{
  "Type": "AthenaBackpackItemDefinition",
  "Name": "BID_945_SleekGlasses_GKUD9",
  "Flags": "RF_Public | RF_Standalone | RF_Transactional | RF_WasLoaded | RF_LoadCompleted",
  "Class": "UScriptClass'AthenaBackpackItemDefinition'",
  "Package": "/BRCosmetics/Athena/Items/Cosmetics/Backpacks/BID_945_SleekGlasses_GKUD9",
  "Properties": {
    "CharacterParts": [
      {
        "ObjectName": "CustomCharacterPart'CP_Backpack_SleekGlasses'",
        "ObjectPath": "/BRCosmetics/Characters/CharacterParts/Backpacks/CP_Backpack_SleekGlasses.1"
      }
    ],
    "ItemPreviewHero": {
      "AssetPathName": "/BRCosmetics/Athena/Items/Cosmetics/Characters/CID_A_335_Athena_Commando_M_SleekGlasses_8SYX2.CID_A_335_Athena_Commando_M_SleekGlasses_8SYX2",
      "SubPathString": ""
    },
    "ShotGridIds": [
      52299
    ],
    "BaseShotGridId": 52299,
    "ItemName": {
      "Namespace": "",
      "Key": "0FD9444B417A88FBB157668BD4737A2C",
      "SourceString": "Sonic Snare",
      "LocalizedString": "Sonic Snare"
    },
    "ItemDescription": {
      "Namespace": "",
      "Key": "4967E46F4A361760A0667BAC84A8F063",
      "SourceString": "Carry the rhythm.",
      "LocalizedString": "Carry the rhythm."
    },
    "ItemShortDescription": {
      "Namespace": "",
      "Key": "255BF55F469A86EABE3F329FA49983B7",
      "SourceString": "Back Bling",
      "LocalizedString": "Back Bling"
    },
    "DataList": [
      {
        "Series": {
          "ObjectName": "FortItemSeriesDefinition'CreatorCollabSeries'",
          "ObjectPath": "/BRCosmetics/Athena/Items/Cosmetics/Series/CreatorCollabSeries.0"
        }
      },
      {
        "MinLevel": 1,
        "MaxLevel": 1
      },
      {
        "Icon": {
          "AssetPathName": "/BRCosmetics/UI/Foundation/Textures/Icons/Backpacks/T-Icon-Backpacks-945-SleekGlasses.T-Icon-Backpacks-945-SleekGlasses",
          "SubPathString": ""
        }
      },
      {
        "LargeIcon": {
          "AssetPathName": "/BRCosmetics/UI/Foundation/Textures/Icons/Backpacks/T-Icon-Backpacks-945-SleekGlasses-L.T-Icon-Backpacks-945-SleekGlasses-L",
          "SubPathString": ""
        }
      },
      {
        "Tags": [
          "Cosmetics.Source.ItemShop",
          "Cosmetics.Filter.Season.19",
          "Cosmetics.Set.AmpleChaos"
        ]
      },
      {
        "Traits": [
          "Item.Trait.SingleStack"
        ]
      },
      {
        "GeneratedTagsIndexes": [
          244,
          277,
          237,
          558,
          367,
          253,
          566,
          254,
          598,
          8,
          251,
          20,
          27,
          638,
          55,
          252,
          717,
          850,
          1090,
          155,
          446,
          1347,
          1377,
          1579,
          2028,
          432,
          445,
          320,
          2689,
          3091,
          3092,
          1582,
          3900,
          3901
        ]
      },
      {
        "Rarity": "EFortRarity::Epic"
      }
    ]
  }
}