{
  "Type": "TextRenderComponent",
  "Name": "NODE_AddTextRenderComponent-1",
  "Flags": "RF_Public | RF_Transactional | RF_ArchetypeObject | RF_WasLoaded | RF_LoadCompleted",
  "Class": "UScriptClass'TextRenderComponent'",
  "Outer": {
    "ObjectName": "BlueprintGeneratedClass'DelMarTrack_BP_C'",
    "ObjectPath": "/DelMarGame/Track/DelMarTrack_BP.1"
  },
  "Properties": {
    "TextMaterial": null,
    "HorizontalAlignment": "EHorizTextAligment::EHTA_Center",
    "VerticalAlignment": "EVerticalTextAligment::EVRTA_TextCenter"
  }
}