{
  "Type": "AthenaItemShopOfferDisplayData",
  "Name": "DAv2_Character_WordUnity",
  "Flags": "RF_Public | RF_Standalone | RF_Transactional | RF_WasLoaded | RF_LoadCompleted",
  "Class": "UScriptClass'AthenaItemShopOfferDisplayData'",
  "Package": "/OfferCatalog/NewDisplayAssets/S40/DAv2_Character_WordUnity",
  "Properties": {
    "ContextualPresentations": [
      {
        "ProductTag": {
          "TagName": "Product.BR"
        },
        "RenderImage": {
          "AssetPathName": "/OfferCatalog/Textures/BattleRoyale/FeaturedItems/Outfit/S40/T_AthenaSoldiers_WordUnity.T_AthenaSoldiers_WordUnity",
          "SubPathString": ""
        },
        "FullTileOverrideRenderImage": {
          "AssetPathName": "",
          "SubPathString": ""
        },
        "OverrideImageMaterial": {
          "AssetPathName": "",
          "SubPathString": ""
        },
        "PoseTestGroup": ""
      },
      {
        "ProductTag": {
          "TagName": "Product.BR"
        },
        "RenderImage": {
          "AssetPathName": "/OfferCatalog/Textures/BattleRoyale/FeaturedItems/Outfit/S40/T_AthenaSoldiers_WordUnity_Phrase.T_AthenaSoldiers_WordUnity_Phrase",
          "SubPathString": ""
        },
        "FullTileOverrideRenderImage": {
          "AssetPathName": "",
          "SubPathString": ""
        },
        "OverrideImageMaterial": {
          "AssetPathName": "",
          "SubPathString": ""
        },
        "PoseTestGroup": ""
      },
      {
        "ProductTag": {
          "TagName": "Product.Juno"
        },
        "RenderImage": {
          "AssetPathName": "/OfferCatalog/Textures/Juno_2dRenders/Figure/Season40/T_UI_Featured_Figure_WordUnity.T_UI_Featured_Figure_WordUnity",
          "SubPathString": ""
        },
        "FullTileOverrideRenderImage": {
          "AssetPathName": "",
          "SubPathString": ""
        },
        "OverrideImageMaterial": {
          "AssetPathName": "",
          "SubPathString": ""
        },
        "PoseTestGroup": ""
      }
    ]
  }
}